osintt.py
osintt-1.0.0.dist-info/METADATA
osintt-1.0.0.dist-info/WHEEL
osintt-1.0.0.dist-info/entry_points.txt
osintt-1.0.0.dist-info/top_level.txt
osintt-1.0.0.dist-info/RECORD
