Metadata-Version: 2.4
Name: osintt
Version: 1.0.0
Summary: OSINT Mobile Number Lookup Tool
Author: Darkboy
Author-email: your-email@example.com
Classifier: Programming Language :: Python :: 3
Classifier: License :: OSI Approved :: MIT License
Classifier: Operating System :: OS Independent
Requires-Dist: requests
Dynamic: author
Dynamic: author-email
Dynamic: classifier
Dynamic: description
Dynamic: requires-dist
Dynamic: summary
